geowise/__init__.py
geowise/common.py
geowise/geowise.py
geowise-0.0.1.dist-info/licenses/LICENSE
geowise-0.0.1.dist-info/METADATA
geowise-0.0.1.dist-info/WHEEL
geowise-0.0.1.dist-info/entry_points.txt
geowise-0.0.1.dist-info/top_level.txt
geowise-0.0.1.dist-info/RECORD
